Metadata-Version: 2.1
Name: pyshode
Version: 1.0
Summary: A python module to custom terminal.
Author: akamedagoat
